market/init.py
market/market.py
market2-0.0.1.dist-info/METADATA
market2-0.0.1.dist-info/WHEEL
market2-0.0.1.dist-info/entry_points.txt
market2-0.0.1.dist-info/top_level.txt
market2-0.0.1.dist-info/RECORD
